{"components_modal_index.md":"68028b39","components_alert_index.md":"86ca6fd7","components_carousel_index.md":"ee935fa2","components_icon_index.md":"642b0811","components_button_index.md":"91775829","components_card_index.md":"08002103","components_index.md":"7e0f07d0","components_input_index.md":"fda6fa60","components_message_index.md":"64146960","components_popover_index.md":"fadab4d6","components_select_index.md":"b6217f3a","guild_install.md":"6e8b58c9","guild_quickstart.md":"fb3ae9cc","index.md":"0eb52e50","components_slider_index.md":"d88473b9"}
